LICENSE
MANIFEST.in
mkpip
setup.py
mkpypkg/__init__.py
mkpypkg/mkpypkg.py
mkpypkg.egg-info/PKG-INFO
mkpypkg.egg-info/SOURCES.txt
mkpypkg.egg-info/dependency_links.txt
mkpypkg.egg-info/top_level.txt