Metadata-Version: 1.0
Name: mkpypkg
Version: 1.0.0
Summary: tool to create python package
Home-page: https://github.com/girish946/mkpypkg
Author: girish joshi
Author-email: girish946@gmail.com
License: UNKNOWN
Keywords: python package setup.py pip
Platform: UNKNOWN
